cfssl/__init__.py
cfssl/cfssl.py
cfssl/defaults.py
cfssl/exceptions.py
cfssl/utils.py
cfssl/models/__init__.py
cfssl/models/certificate_request.py
cfssl/models/config_client.py
cfssl/models/config_key.py
cfssl/models/config_mixer.py
cfssl/models/config_server.py
cfssl/models/host.py
cfssl/models/policy_auth.py
cfssl/models/policy_sign.py
cfssl/models/policy_use.py
cfssl/models/subject_info.py
cfssl/tests/__init__.py
cfssl/tests/test_certificate_request.py
cfssl/tests/test_cfssl.py
cfssl/tests/test_config_client.py
cfssl/tests/test_config_key.py
cfssl/tests/test_config_mixer.py
cfssl/tests/test_host.py
cfssl/tests/test_policy_auth.py
cfssl/tests/test_policy_sign.py
cfssl/tests/test_policy_use.py
cfssl/tests/test_subject_info.py
cfssl/tests/test_utils.py
cfssl-0.0.3b243.dist-info/DESCRIPTION.rst
cfssl-0.0.3b243.dist-info/METADATA
cfssl-0.0.3b243.dist-info/RECORD
cfssl-0.0.3b243.dist-info/WHEEL
cfssl-0.0.3b243.dist-info/metadata.json
cfssl-0.0.3b243.dist-info/top_level.txt
