Metadata-Version: 2.0
Name: cfssl
Version: 0.0.3b243
Summary: This library will allow you to interact with a remote CFSSL server using Python.
Home-page: https://laslabs.github.io/python-cfssl
Author: LasLabs Inc.
Author-email: support@laslabs.com
License: MIT
Download-URL: https://github.com/LasLabs/python-cfssl
Platform: UNKNOWN
Classifier: Development Status :: 4 - Beta
Classifier: Environment :: Console
Classifier: Intended Audience :: Developers
Classifier: License :: OSI Approved :: MIT License
Classifier: Programming Language :: Python
Classifier: Programming Language :: Python :: 2
Classifier: Programming Language :: Python :: 2.7
Classifier: Programming Language :: Python :: 3
Classifier: Programming Language :: Python :: 3.4
Classifier: Programming Language :: Python :: 3.5
Classifier: Programming Language :: Python :: 3.6
Classifier: Topic :: Software Development :: Libraries :: Python Modules
Requires-Dist: requests
